conftest.py
frequenz/api/common/py.typed
frequenz/api/common/pagination/py.typed
frequenz/api/weather/__init__.py
frequenz/api/weather/conftest.py
frequenz/api/weather/py.typed
frequenz/api/weather/v1/__init__.py
frequenz/api/weather/v1/weather_pb2.py
frequenz/api/weather/v1/weather_pb2.pyi
frequenz/api/weather/v1/weather_pb2_grpc.py
frequenz/api/weather/v1/weather_pb2_grpc.pyi
frequenz/client/weather/__init__.py
frequenz_api_weather-0.13.0.dist-info/LICENSE
frequenz_api_weather-0.13.0.dist-info/METADATA
frequenz_api_weather-0.13.0.dist-info/WHEEL
frequenz_api_weather-0.13.0.dist-info/top_level.txt
frequenz_api_weather-0.13.0.dist-info/RECORD
