Metadata-Version: 2.1
Name: frequenz-api-weather
Version: 0.13.0
Summary: Frequenz gRPC API for retrieving weather forecasts.
Author-email: Frequenz Energy-as-a-Service GmbH <floss@frequenz.com>
License: MIT
Project-URL: Documentation, https://frequenz-floss.github.io/frequenz-api-weather/
Project-URL: Changelog, https://github.com/frequenz-floss/frequenz-api-weather/releases
Project-URL: Issues, https://github.com/frequenz-floss/frequenz-api-weather/issues
Project-URL: Repository, https://github.com/frequenz-floss/frequenz-api-weather
Project-URL: Support, https://github.com/frequenz-floss/frequenz-api-weather/discussions/categories/support
Keywords: frequenz,python,api,grpc,protobuf,rpc,weather
Classifier: Development Status :: 3 - Alpha
Classifier: Intended Audience :: Developers
Classifier: License :: OSI Approved :: MIT License
Classifier: Programming Language :: Python :: 3
Classifier: Programming Language :: Python :: 3 :: Only
Classifier: Topic :: Software Development :: Libraries
Classifier: Typing :: Typed
Requires-Python: <4,>=3.11
License-File: LICENSE
Requires-Dist: frequenz-api-common<0.7.0,>=0.6.0
Requires-Dist: googleapis-common-protos<2,>=1.56.4
Requires-Dist: protobuf<6,>=4.25.3
Requires-Dist: grpcio<2,>=1.54.2
Provides-Extra: dev
Requires-Dist: frequenz-api-weather[dev-flake8,dev-formatting,dev-mkdocs,dev-mypy,dev-noxfile,dev-pylint,dev-pytest]; extra == "dev"
Provides-Extra: dev-flake8
Requires-Dist: flake8==7.0.0; extra == "dev-flake8"
Requires-Dist: flake8-docstrings==1.7.0; extra == "dev-flake8"
Requires-Dist: flake8-pyproject==1.2.3; extra == "dev-flake8"
Requires-Dist: pydoclint==0.6.5; extra == "dev-flake8"
Requires-Dist: pydocstyle==6.3.0; extra == "dev-flake8"
Provides-Extra: dev-formatting
Requires-Dist: black==24.4.2; extra == "dev-formatting"
Requires-Dist: isort==5.12.0; extra == "dev-formatting"
Provides-Extra: dev-mkdocs
Requires-Dist: black==24.4.2; extra == "dev-mkdocs"
Requires-Dist: Markdown==3.7; extra == "dev-mkdocs"
Requires-Dist: mike==2.1.3; extra == "dev-mkdocs"
Requires-Dist: mkdocs-gen-files==0.5.0; extra == "dev-mkdocs"
Requires-Dist: mkdocs-literate-nav==0.6.2; extra == "dev-mkdocs"
Requires-Dist: mkdocs-macros-plugin==1.0.4; extra == "dev-mkdocs"
Requires-Dist: mkdocs-material==9.4.4; extra == "dev-mkdocs"
Requires-Dist: mkdocstrings[python]==0.29.1; extra == "dev-mkdocs"
Requires-Dist: mkdocstrings-python==1.16.8; extra == "dev-mkdocs"
Requires-Dist: frequenz-repo-config[api]==0.13.1; extra == "dev-mkdocs"
Provides-Extra: dev-mypy
Requires-Dist: mypy==1.5.1; extra == "dev-mypy"
Requires-Dist: grpc-stubs==1.53.0.5; extra == "dev-mypy"
Requires-Dist: types-Markdown==3.7.0.20250322; extra == "dev-mypy"
Requires-Dist: frequenz-api-weather[dev-mkdocs,dev-noxfile,dev-pytest]; extra == "dev-mypy"
Provides-Extra: dev-noxfile
Requires-Dist: nox==2025.2.9; extra == "dev-noxfile"
Requires-Dist: frequenz-repo-config[api]==0.13.1; extra == "dev-noxfile"
Provides-Extra: dev-pylint
Requires-Dist: pylint==3.0.2; extra == "dev-pylint"
Requires-Dist: frequenz-api-weather[dev-mkdocs,dev-noxfile,dev-pytest]; extra == "dev-pylint"
Provides-Extra: dev-pytest
Requires-Dist: pytest==8.3.5; extra == "dev-pytest"
Requires-Dist: frequenz-repo-config[extra-lint-examples]==0.13.1; extra == "dev-pytest"
Requires-Dist: pytest-asyncio==0.26.0; extra == "dev-pytest"
